sundaram/__init__.py
sundaram/__main__.py
sundaram/calculate.py
sundaram/validate.py
sundaram/test/test_sundaram.py
sundaram-1.0.1.data/scripts/sundaram_script.py
sundaram-1.0.1.data/scripts/test_sundaram.py
sundaram-1.0.1.dist-info/METADATA
sundaram-1.0.1.dist-info/WHEEL
sundaram-1.0.1.dist-info/top_level.txt
sundaram-1.0.1.dist-info/RECORD
