Metadata-Version: 2.1
Name: sundaram
Version: 1.0.1
Summary: Расчет решета сундарама
License: MIT License
